anduschain/__init__.py
anduschain/middleware.py
anduschain/singners.py
anduschain-1.0.1.dist-info/METADATA
anduschain-1.0.1.dist-info/WHEEL
anduschain-1.0.1.dist-info/top_level.txt
anduschain-1.0.1.dist-info/RECORD
